{\n  \"scriptInfo\": {\n    \"nome\": \"Check-up de TI\",\n    \"versao\": \"1.0.0\",\n    \"descricao\": \"Script PowerShell para monitorar status de dispositivos de rede\",\n    \"autor\": \"Equipe de TI\",\n    \"data\": \"2026-04-22\"\n  },\n  \"dispositivos\": [\n    {\n      \"ip\": \"192.168.1.1\",\n      \"nome\": \"Roteador (Gateway)\",\n      \"descricao\": \"Gateway padrão da rede local\",\n      \"ativo\": true\n    },\n    {\n      \"ip\": \"8.8.8.8\",\n      \"nome\": \"Internet\",\n      \"descricao\": \"Conectividade externa (Google DNS)\",\n      \"ativo\": true\n    },\n    {\n      \"ip\": \"192.168.1.50\",\n      \"nome\": \"Impressora\",\n      \"descricao\": \"Dispositivo de impressão em rede\",\n      \"ativo\": true\n    }\n  ],\n  \"configuracoes\": {\n    \"timeout\": 1,\n    \"tentativas\": 1,\n    \"salvarEm\": \"Desktop\",\n    \"nomeRelatorio\": \"Relatorio_Rede.html\",\n    \"formatoData\": \"dd/MM/yyyy HH:mm:ss\"\n  },\n  \"estilos\": {\n    \"cores\": {\n      \"online\": \"green\",\n      \"offline\": \"red\",\n      \"tabela\": \"#ddd\"\n    },\n    \"fonte\": \"sans-serif\",\n    \"tamanho\": \"14px\"\n  }\n}\n"